cloud_github/__init__.py
cloud_github/ghe.py
cloud_github/ghe_extension.py
cloud_github/logger.py
cloud_github-0.0.1.dist-info/LICENSE.txt
cloud_github-0.0.1.dist-info/METADATA
cloud_github-0.0.1.dist-info/WHEEL
cloud_github-0.0.1.dist-info/top_level.txt
cloud_github-0.0.1.dist-info/RECORD
